imgscrapper/__init__.py
imgscrapper/__main__.py
imgscrapper/errors.py
imgscrapper/imgscrapper.py
imgscrapper/utils.py
just_another_imgscrapper-0.1.2.dist-info/LICENSE
just_another_imgscrapper-0.1.2.dist-info/METADATA
just_another_imgscrapper-0.1.2.dist-info/WHEEL
just_another_imgscrapper-0.1.2.dist-info/entry_points.txt
just_another_imgscrapper-0.1.2.dist-info/top_level.txt
just_another_imgscrapper-0.1.2.dist-info/RECORD
