Metadata-Version: 2.1
Name: just-another-imgscrapper
Version: 0.1.2
Summary: A utility for scrapping images from a HTML doc from  a URL.
Home-page: https://github.com/deshrit/just-another-imgscrapper
Author: Deshrit Baral
Author-email: deshritbaral@gmail.com
License: MIT
Keywords: image,scrapper,asyncio,httpx,beautifulsoup4,lxml
Classifier: Programming Language :: Python
Classifier: Programming Language :: Python :: 3
Classifier: Programming Language :: Python :: 3.7
Classifier: Programming Language :: Python :: 3.8
Classifier: Programming Language :: Python :: 3.9
Classifier: Programming Language :: Python :: 3.10
Classifier: Programming Language :: Python :: 3.11
Requires-Python: >=3.7
License-File: LICENSE
Requires-Dist: aiofiles (>=23.1.0)
Requires-Dist: beautifulsoup4 (>=4.12.2)
Requires-Dist: httpx (>=0.24.1)
Requires-Dist: lxml (>=4.9.2)
Provides-Extra: dev
Requires-Dist: coverage ; extra == 'dev'
Requires-Dist: flake8 ; extra == 'dev'
Requires-Dist: mypy ; extra == 'dev'
Requires-Dist: pre-commit ; extra == 'dev'
Requires-Dist: tox ; extra == 'dev'
